{"special":"The problem can be corrected by updating your system to the following package versions:\nAfter a standard system update you need to restart your session to make\nall the necessary changes.","threat":["If a remote attacker were able to perform a man-in-the-middle attack, this flaw could be exploited to alter or compromise confidential information.."],"update":{"11.10":[{"package":"ubuntuone-couch","version":"0.3.0-0ubuntu2.1"}]},"date":"March 01, 2012","usn":"USN-1381-1","CVEs":[],"info":"ubuntuone-couch vulnerability"}