{"special":"The problem can be corrected by updating your system to the following package versions:\nAfter a standard system update you need to reboot your computer to make\nall the necessary changes.","threat":["A local attacker could exploit this race by using chown on a  setuid-user-binary to gain administrative privileges.."],"update":{"14.04":[{"version":"3.13.0-52.86","package":"linux-image-3.13.0-52-generic"},{"version":"3.13.0-52.86","package":"linux-image-3.13.0-52-generic-lpae"},{"version":"3.13.0-52.86","package":"linux-image-3.13.0-52-lowlatency"},{"package":"linux-image-3.13.0-52-powerpc-e500","version":"3.13.0-52.86"},{"package":"linux-image-3.13.0-52-powerpc-e500mc","version":"3.13.0-52.86"},{"package":"linux-image-3.13.0-52-powerpc-smp","version":"3.13.0-52.86"},{"package":"linux-image-3.13.0-52-powerpc64-emb","version":"3.13.0-52.86"},{"package":"linux-image-3.13.0-52-powerpc64-smp","version":"3.13.0-52.86"}]},"date":"May 09, 2015","usn":"USN-2598-2","CVEs":[],"info":"linux vulnerability"}